multicodec/__init__.py
multicodec/constants.py
multicodec/multicodec.py
py_multicodec-0.1.3.dist-info/DESCRIPTION.rst
py_multicodec-0.1.3.dist-info/METADATA
py_multicodec-0.1.3.dist-info/RECORD
py_multicodec-0.1.3.dist-info/WHEEL
py_multicodec-0.1.3.dist-info/metadata.json
py_multicodec-0.1.3.dist-info/top_level.txt
