Metadata-Version: 2.0
Name: py-multicodec
Version: 0.1.3
Summary: Multicodec implementation in Python
Home-page: https://github.com/multiformats/py-multicodec
Author: Dhruv Baldawa
Author-email: dhruv@dhruvb.com
License: MIT license
Keywords: multicodec
Platform: UNKNOWN
Classifier: Development Status :: 2 - Pre-Alpha
Classifier: Intended Audience :: Developers
Classifier: License :: OSI Approved :: MIT License
Classifier: Natural Language :: English
Classifier: Programming Language :: Python :: 3.4
Classifier: Programming Language :: Python :: 3.5
Classifier: Programming Language :: Python :: 3.6
Requires-Dist: morphys (>=1.0,<2.0)
Requires-Dist: six (<2.0,>=1.10.0)
Requires-Dist: varint (>=1.0.2,<2.0.0)
